nablafx/__init__.py
nablafx/py.typed
nablafx/callbacks/__init__.py
nablafx/callbacks/audio_chain_logging.py
nablafx/callbacks/audio_logging.py
nablafx/callbacks/fad_computation.py
nablafx/callbacks/frequency_response.py
nablafx/callbacks/metrics_logging.py
nablafx/callbacks/parameter_logging.py
nablafx/controllers/__init__.py
nablafx/controllers/controllers.py
nablafx/core/__init__.py
nablafx/core/base_system.py
nablafx/core/blackbox_system.py
nablafx/core/greybox_system.py
nablafx/core/interfaces.py
nablafx/core/models.py
nablafx/data/__init__.py
nablafx/data/datamodules.py
nablafx/data/datasets.py
nablafx/data/transforms.py
nablafx/evaluation/__init__.py
nablafx/evaluation/flexible_loss.py
nablafx/evaluation/registry.py
nablafx/evaluation/functions/__init__.py
nablafx/evaluation/functions/audio_specific.py
nablafx/evaluation/functions/frequency_domain.py
nablafx/evaluation/functions/time_domain.py
nablafx/processors/__init__.py
nablafx/processors/blocks.py
nablafx/processors/components.py
nablafx/processors/ddsp.py
nablafx/processors/dsp.py
nablafx/processors/gcn.py
nablafx/processors/lstm.py
nablafx/processors/s4.py
nablafx/processors/siren.py
nablafx/processors/tcn.py
nablafx/utils/__init__.py
nablafx/utils/plotting.py
nablafx/utils/utilities.py
nablafx-1.0.0.data/data/share/nablafx/weights/rationals_config.json
nablafx-1.0.0.data/data/share/nablafx/weights/static_fir_filter_t128-h32-l5.pt
nablafx-1.0.0.data/data/share/nablafx/weights/static_fir_filter_t256-h16-l5.pt
nablafx-1.0.0.data/data/share/nablafx/weights/static_fir_filter_t256-h32-l3.pt
nablafx-1.0.0.data/data/share/nablafx/weights/static_fir_filter_t256-h32-l4.pt
nablafx-1.0.0.data/data/share/nablafx/weights/static_fir_filter_t256-h32-l5.pt
nablafx-1.0.0.data/data/share/nablafx/weights/static_fir_filter_t256-h32-l6.pt
nablafx-1.0.0.data/data/share/nablafx/weights/static_fir_filter_t64-h32-l3.pt
nablafx-1.0.0.data/data/share/nablafx/weights/static_fir_filter_t64-h32-l5.pt
nablafx-1.0.0.dist-info/licenses/LICENSE
nablafx-1.0.0.dist-info/METADATA
nablafx-1.0.0.dist-info/WHEEL
nablafx-1.0.0.dist-info/top_level.txt
nablafx-1.0.0.dist-info/RECORD
