Metadata-Version: 2.4
Name: nablafx
Version: 1.0.0
Summary: Differentiable black-box and gray-box audio effects modeling framework
Author-email: Marco Comunità <m.comunita@qmul.ac.uk>
Maintainer-email: Marco Comunità <m.comunita@qmul.ac.uk>
License: MIT License
Project-URL: Homepage, https://github.com/mcomunita/nablafx
Project-URL: Documentation, https://github.com/mcomunita/nablafx#readme
Project-URL: Repository, https://github.com/mcomunita/nablafx.git
Project-URL: Bug Tracker, https://github.com/mcomunita/nablafx/issues
Project-URL: Installation Guide, https://github.com/mcomunita/nablafx/blob/master/INSTALL.md
Project-URL: Paper, https://arxiv.org/abs/2502.11668
Keywords: audio,audio-effects,deep-learning,differentiable-dsp,pytorch,audio-processing,neural-audio,black-box-modeling,gray-box-modeling,machine-learning
Classifier: Development Status :: 4 - Beta
Classifier: Intended Audience :: Science/Research
Classifier: Intended Audience :: Developers
Classifier: License :: OSI Approved :: Apache Software License
Classifier: Programming Language :: Python :: 3
Classifier: Programming Language :: Python :: 3.9
Classifier: Topic :: Scientific/Engineering :: Artificial Intelligence
Classifier: Topic :: Multimedia :: Sound/Audio :: Analysis
Classifier: Topic :: Software Development :: Libraries :: Python Modules
Requires-Python: >=3.9
License-File: LICENSE
Requires-Dist: auraloss>=0.4.0
Requires-Dist: einops>=0.8.0
Requires-Dist: frechet_audio_distance
Requires-Dist: jsonargparse[signatures]>=4.27.7
Requires-Dist: lightning>=2.3.2
Requires-Dist: lightning-utilities>=0.11.3
Requires-Dist: matplotlib>=3.9.1
Requires-Dist: natsort
Requires-Dist: numpy<2.0,>=1.26.4
Requires-Dist: scipy>=1.13.1
Requires-Dist: torch>=2.2.2
Requires-Dist: torchaudio>=2.2.2
Requires-Dist: torchmetrics>=1.4.0
Requires-Dist: torchvision>=0.17.2
Requires-Dist: typing-extensions>=4.12.2
Requires-Dist: wandb>=0.17.4
Provides-Extra: dev
Requires-Dist: pytest>=7.0; extra == "dev"
Requires-Dist: pytest-cov>=4.0; extra == "dev"
Requires-Dist: black>=23.0; extra == "dev"
Requires-Dist: isort>=5.12; extra == "dev"
Requires-Dist: flake8>=6.0; extra == "dev"
Requires-Dist: mypy>=1.0; extra == "dev"
Provides-Extra: docs
Requires-Dist: sphinx>=6.0; extra == "docs"
Requires-Dist: sphinx-rtd-theme>=1.2; extra == "docs"
Dynamic: license-file
